{
  "vix": [
    {
      "date": "2026-04-10",
      "value": 21.04
    }
  ],
  "us10y": [
    {
      "date": "2026-04-10",
      "value": 4.29
    }
  ],
  "us2y": [
    {
      "date": "2026-04-10",
      "value": 3.79
    }
  ],
  "spread_2_10": [
    {
      "date": "2026-04-10",
      "value": 0.51
    }
  ],
  "tga": [
    {
      "date": "2026-04-10",
      "value": 748376.0
    }
  ],
  "rrp": [
    {
      "date": "2026-04-10",
      "value": 0.402
    }
  ],
  "m2": [
    {
      "date": "2026-04-10",
      "value": 22667.3
    }
  ],
  "fed_balance": [
    {
      "date": "2026-04-10",
      "value": 6693871.0
    }
  ]
}